sclbl/__init__.py
sclbl/__main__.py
sclbl/_globals.py
sclbl/cli.py
sclbl/version.py
sclbl-0.0.1.dist-info/LICENSE
sclbl-0.0.1.dist-info/METADATA
sclbl-0.0.1.dist-info/WHEEL
sclbl-0.0.1.dist-info/entry_points.txt
sclbl-0.0.1.dist-info/top_level.txt
sclbl-0.0.1.dist-info/RECORD
