Metadata-Version: 2.1
Name: sclbl
Version: 0.0.1
Summary: Python package for uploading sklearn and onnx models to Scailable toolchain.
Home-page: https://www.scailable.net
Author: Maurits Kaptein
Author-email: maurits.kaptein@scailable.net
License: UNKNOWN
Platform: UNKNOWN
Classifier: Programming Language :: Python :: 3
Classifier: License :: OSI Approved :: MIT License
Classifier: Operating System :: OS Independent
Requires-Python: >=3.7
Requires-Dist: click
Requires-Dist: sclblpy
